plotly_3d_primitives/__init__.py
plotly_3d_primitives/shapes.py
plotly_3d_primitives-0.4.0.dist-info/licenses/LICENSE
plotly_3d_primitives-0.4.0.dist-info/WHEEL
plotly_3d_primitives-0.4.0.dist-info/METADATA
plotly_3d_primitives-0.4.0.dist-info/RECORD
